rmm/GIT_COMMIT
rmm/VERSION
rmm/__init__.py
rmm/_version.py
rmm/py.typed
rmm/rmm.py
rmm/statistics.py
rmm/_cuda/CMakeLists.txt
rmm/_cuda/__init__.pxd
rmm/_cuda/gpu.py
rmm/_cuda/stream.pxd
rmm/allocators/__init__.py
rmm/allocators/cupy.py
rmm/allocators/numba.py
rmm/allocators/torch.py
rmm/librmm/CMakeLists.txt
rmm/librmm/__init__.py
rmm/librmm/_logger.cpython-311-aarch64-linux-gnu.so
rmm/librmm/_logger.pxd
rmm/librmm/_logger.pyx
rmm/librmm/_torch_allocator.cpp
rmm/librmm/_torch_allocator.so
rmm/librmm/cuda_stream.pxd
rmm/librmm/cuda_stream_pool.pxd
rmm/librmm/cuda_stream_view.pxd
rmm/librmm/device_buffer.pxd
rmm/librmm/device_uvector.pxd
rmm/librmm/memory_resource.pxd
rmm/librmm/per_device_resource.pxd
rmm/mr/__init__.py
rmm/mr/experimental.py
rmm/pylibrmm/CMakeLists.txt
rmm/pylibrmm/__init__.py
rmm/pylibrmm/cuda_stream.cpython-311-aarch64-linux-gnu.so
rmm/pylibrmm/cuda_stream.pxd
rmm/pylibrmm/cuda_stream.pyx
rmm/pylibrmm/cuda_stream_pool.cpython-311-aarch64-linux-gnu.so
rmm/pylibrmm/cuda_stream_pool.pxd
rmm/pylibrmm/cuda_stream_pool.pyx
rmm/pylibrmm/device_buffer.cpython-311-aarch64-linux-gnu.so
rmm/pylibrmm/device_buffer.pxd
rmm/pylibrmm/device_buffer.pyx
rmm/pylibrmm/helper.cpython-311-aarch64-linux-gnu.so
rmm/pylibrmm/helper.pxd
rmm/pylibrmm/helper.pyx
rmm/pylibrmm/logger.cpython-311-aarch64-linux-gnu.so
rmm/pylibrmm/logger.pyx
rmm/pylibrmm/stream.cpython-311-aarch64-linux-gnu.so
rmm/pylibrmm/stream.pxd
rmm/pylibrmm/stream.pyx
rmm/pylibrmm/utils.cpython-311-aarch64-linux-gnu.so
rmm/pylibrmm/utils.pxd
rmm/pylibrmm/utils.pyx
rmm/pylibrmm/memory_resource/CMakeLists.txt
rmm/pylibrmm/memory_resource/__init__.pxd
rmm/pylibrmm/memory_resource/__init__.py
rmm/pylibrmm/memory_resource/_memory_resource.cpython-311-aarch64-linux-gnu.so
rmm/pylibrmm/memory_resource/_memory_resource.pxd
rmm/pylibrmm/memory_resource/_memory_resource.pyx
rmm/pylibrmm/memory_resource/experimental.cpython-311-aarch64-linux-gnu.so
rmm_cu12-25.12.0.dist-info/METADATA
rmm_cu12-25.12.0.dist-info/WHEEL
rmm_cu12-25.12.0.dist-info/RECORD
rmm_cu12-25.12.0.dist-info/licenses/LICENSE
